longformer_embedder/__init__.py
longformer_embedder/core.py
longformer_embedder-0.1.2.dist-info/licenses/LICENSE
longformer_embedder-0.1.2.dist-info/METADATA
longformer_embedder-0.1.2.dist-info/WHEEL
longformer_embedder-0.1.2.dist-info/top_level.txt
longformer_embedder-0.1.2.dist-info/RECORD
