Metadata-Version: 2.4
Name: longformer-embedder
Version: 0.1.2
Summary: A small wrapper for generating Longformer embeddings.
Author-email: Yash Garg <gargyash195@gmail.com>
License: MIT
Keywords: longformer,transformers,embeddings,nlp
Classifier: Programming Language :: Python :: 3
Classifier: Programming Language :: Python :: 3 :: Only
Classifier: License :: OSI Approved :: MIT License
Classifier: Intended Audience :: Developers
Classifier: Topic :: Scientific/Engineering :: Artificial Intelligence
Requires-Python: >=3.8
License-File: LICENSE
Requires-Dist: numpy>=1.21
Requires-Dist: torch>=1.12
Requires-Dist: transformers>=4.0
Requires-Dist: tqdm
Dynamic: license-file
